setup.py
thematch/__init__.py
thematch/match.py
thematch/process.py
thematch/utils.py
thematch.egg-info/PKG-INFO
thematch.egg-info/SOURCES.txt
thematch.egg-info/dependency_links.txt
thematch.egg-info/requires.txt
thematch.egg-info/top_level.txt