Metadata-Version: 2.1
Name: thematch
Version: 2.0
Summary: thematch
Home-page: https://github.com/ExpertOfAI/thematch
Author: ExpertOfAI
License: MIT
Classifier: Programming Language :: Python :: 3
Classifier: License :: OSI Approved :: MIT License
Classifier: Operating System :: OS Independent
Requires-Python: >=3.6
Requires-Dist: rapidfuzz
